databricks_runtime_python_env/__init__.py
databricks_runtime_python_env/spark_env.py
databricks_runtime_python_env/version.py
databricks_runtime_python_env-0.1.0.dist-info/METADATA
databricks_runtime_python_env-0.1.0.dist-info/WHEEL
databricks_runtime_python_env-0.1.0.dist-info/top_level.txt
databricks_runtime_python_env-0.1.0.dist-info/RECORD
