Metadata-Version: 2.1
Name: databricks-runtime-python-env
Version: 0.1.0
Summary: Python dependencies installed on Databricks Runtimes
Author-email: George Marlow <georgewamarlow@gmail.com>
Classifier: Programming Language :: Python :: 3
Classifier: License :: OSI Approved :: MIT License
Classifier: Operating System :: OS Independent
Requires-Python: ==3.10
Requires-Dist: anyio==3.5.0
Requires-Dist: argon2-cffi==21.3.0
Requires-Dist: argon2-cffi-bindings==21.2.0
Requires-Dist: asttokens==2.0.5
Requires-Dist: attrs==22.1.0
Requires-Dist: backcall==0.2.0
Requires-Dist: beautifulsoup4==4.11.1
Requires-Dist: black==22.6.0
Requires-Dist: bleach==4.1.0
Requires-Dist: blinker==1.4
Requires-Dist: boto3==1.24.28
Requires-Dist: botocore==1.27.96
Requires-Dist: certifi==2022.12.7
Requires-Dist: cffi==1.15.1
Requires-Dist: chardet==4.0.0
Requires-Dist: charset-normalizer==2.0.4
Requires-Dist: click==8.0.4
Requires-Dist: comm==0.1.2
Requires-Dist: contourpy==1.0.5
Requires-Dist: cryptography==39.0.1
Requires-Dist: cycler==0.11.0
Requires-Dist: Cython==0.29.32
Requires-Dist: databricks-sdk==0.1.6
Requires-Dist: dbus-python==1.2.18
Requires-Dist: debugpy==1.6.7
Requires-Dist: decorator==5.1.1
Requires-Dist: defusedxml==0.7.1
Requires-Dist: distlib==0.3.7
Requires-Dist: docstring-to-markdown==0.11
Requires-Dist: entrypoints==0.4
Requires-Dist: executing==0.8.3
Requires-Dist: facets-overview==1.1.1
Requires-Dist: fastjsonschema==2.19.1
Requires-Dist: filelock==3.13.1
Requires-Dist: fonttools==4.25.0
Requires-Dist: googleapis-common-protos==1.62.0
Requires-Dist: grpcio==1.48.2
Requires-Dist: grpcio-status==1.48.1
Requires-Dist: httplib2==0.20.2
Requires-Dist: idna==3.4
Requires-Dist: importlib-metadata==4.6.4
Requires-Dist: ipykernel==6.25.0
Requires-Dist: ipython==8.14.0
Requires-Dist: ipython-genutils==0.2.0
Requires-Dist: ipywidgets==7.7.2
Requires-Dist: jedi==0.18.1
Requires-Dist: jeepney==0.7.1
Requires-Dist: Jinja2==3.1.2
Requires-Dist: jmespath==0.10.0
Requires-Dist: joblib==1.2.0
Requires-Dist: jsonschema==4.17.3
Requires-Dist: jupyter-client==7.3.4
Requires-Dist: jupyter-server==1.23.4
Requires-Dist: jupyter_core==5.2.0
Requires-Dist: jupyterlab-pygments==0.1.2
Requires-Dist: jupyterlab-widgets==1.0.0
Requires-Dist: keyring==23.5.0
Requires-Dist: kiwisolver==1.4.4
Requires-Dist: launchpadlib==1.10.16
Requires-Dist: lazr.restfulclient==0.14.4
Requires-Dist: lazr.uri==1.0.6
Requires-Dist: lxml==4.9.1
Requires-Dist: MarkupSafe==2.1.1
Requires-Dist: matplotlib==3.7.0
Requires-Dist: matplotlib-inline==0.1.6
Requires-Dist: mccabe==0.7.0
Requires-Dist: mistune==0.8.4
Requires-Dist: more-itertools==8.10.0
Requires-Dist: mypy-extensions==0.4.3
Requires-Dist: nbclassic==0.5.2
Requires-Dist: nbclient==0.5.13
Requires-Dist: nbconvert==6.5.4
Requires-Dist: nbformat==5.7.0
Requires-Dist: nest-asyncio==1.5.6
Requires-Dist: nodeenv==1.8.0
Requires-Dist: notebook==6.5.2
Requires-Dist: notebook_shim==0.2.2
Requires-Dist: numpy==1.23.5
Requires-Dist: oauthlib==3.2.0
Requires-Dist: packaging==23.2
Requires-Dist: pandas==1.5.3
Requires-Dist: pandocfilters==1.5.0
Requires-Dist: parso==0.8.3
Requires-Dist: pathspec==0.10.3
Requires-Dist: patsy==0.5.3
Requires-Dist: pexpect==4.8.0
Requires-Dist: pickleshare==0.7.5
Requires-Dist: Pillow==9.4.0
Requires-Dist: pip==22.3.1
Requires-Dist: platformdirs==2.5.2
Requires-Dist: plotly==5.9.0
Requires-Dist: pluggy==1.0.0
Requires-Dist: prometheus-client==0.14.1
Requires-Dist: prompt-toolkit==3.0.36
Requires-Dist: protobuf==4.24.0
Requires-Dist: psutil==5.9.0
Requires-Dist: psycopg2==2.9.3
Requires-Dist: ptyprocess==0.7.0
Requires-Dist: pure-eval==0.2.2
Requires-Dist: pyarrow==8.0.0
Requires-Dist: pyarrow-hotfix==0.5
Requires-Dist: pycparser==2.21
Requires-Dist: pydantic==1.10.6
Requires-Dist: pyflakes==3.1.0
Requires-Dist: Pygments==2.11.2
Requires-Dist: PyGObject==3.42.1
Requires-Dist: PyJWT==2.3.0
Requires-Dist: pyodbc==4.0.32
Requires-Dist: pyparsing==3.0.9
Requires-Dist: pyright==1.1.294
Requires-Dist: pyrsistent==0.18.0
Requires-Dist: python-dateutil==2.8.2
Requires-Dist: python-lsp-jsonrpc==1.1.1
Requires-Dist: python-lsp-server==1.8.0
Requires-Dist: pytoolconfig==1.2.5
Requires-Dist: pytz==2022.7
Requires-Dist: pyzmq==23.2.0
Requires-Dist: requests==2.28.1
Requires-Dist: rope==1.7.0
Requires-Dist: s3transfer==0.6.2
Requires-Dist: scikit-learn==1.1.1
Requires-Dist: scipy==1.10.0
Requires-Dist: seaborn==0.12.2
Requires-Dist: SecretStorage==3.3.1
Requires-Dist: Send2Trash==1.8.0
Requires-Dist: setuptools==65.6.3
Requires-Dist: six==1.16.0
Requires-Dist: sniffio==1.2.0
Requires-Dist: soupsieve==2.3.2.post1
Requires-Dist: ssh-import-id==5.11
Requires-Dist: stack-data==0.2.0
Requires-Dist: statsmodels==0.13.5
Requires-Dist: tenacity==8.1.0
Requires-Dist: terminado==0.17.1
Requires-Dist: threadpoolctl==2.2.0
Requires-Dist: tinycss2==1.2.1
Requires-Dist: tokenize-rt==4.2.1
Requires-Dist: tomli==2.0.1
Requires-Dist: tornado==6.1
Requires-Dist: traitlets==5.7.1
Requires-Dist: typing_extensions==4.4.0
Requires-Dist: ujson==5.4.0
Requires-Dist: unattended-upgrades==0.1
Requires-Dist: urllib3==1.26.14
Requires-Dist: virtualenv==20.16.7
Requires-Dist: wadllib==1.3.6
Requires-Dist: wcwidth==0.2.5
Requires-Dist: webencodings==0.5.1
Requires-Dist: websocket-client==0.58.0
Requires-Dist: whatthepatch==1.0.2
Requires-Dist: wheel==0.38.4
Requires-Dist: widgetsnbextension==3.6.1
Requires-Dist: yapf==0.33.0
Requires-Dist: zipp==1.0.0
